woudc_extcsv/__init__.py
woudc_extcsv/table_configuration.csv
woudc_extcsv-0.3.1.dist-info/LICENSE.md
woudc_extcsv-0.3.1.dist-info/METADATA
woudc_extcsv-0.3.1.dist-info/WHEEL
woudc_extcsv-0.3.1.dist-info/top_level.txt
woudc_extcsv-0.3.1.dist-info/RECORD
