Metadata-Version: 2.1
Name: woudc-extcsv
Version: 0.3.1
Summary: Python package providing read/write support of the WOUDC Extended CSV format.
Home-page: https://github.com/woudc/woudc-extcsv
Author: Meteorological Service of Canada
Author-email: thinesh.sornalingam@canada.ca
Maintainer: Meteorological Service of Canada
Maintainer-email: thinesh.sornalingam@canada.ca
License: MIT
Keywords: woudc ozone uv ultra-violet WMO Extended CSV
Platform: all
Classifier: Development Status :: 4 - Beta
Classifier: Environment :: Console
Classifier: Intended Audience :: Developers
Classifier: Intended Audience :: Science/Research
Classifier: License :: OSI Approved :: MIT License
Classifier: Operating System :: OS Independent
Classifier: Programming Language :: Python
Classifier: Topic :: Scientific/Engineering :: Atmospheric Science
Requires-Dist: pywoudc
